README.md
setup.py
custom_erp_connector.egg-info/PKG-INFO
custom_erp_connector.egg-info/SOURCES.txt
custom_erp_connector.egg-info/dependency_links.txt
custom_erp_connector.egg-info/entry_points.txt
custom_erp_connector.egg-info/requires.txt
custom_erp_connector.egg-info/top_level.txt
erp_connector/__init__.py
erp_connector/scheduler.py
erp_connector/clients/__init__.py
erp_connector/clients/euclid_client.py
erp_connector/clients/one_integration_client.py
erp_connector/config/__init__.py
erp_connector/config/config_loader.py
erp_connector/db/__init__.py
erp_connector/db/db_connector.py
erp_connector/db/db_loader.py
erp_connector/db/mssql_connector.py
erp_connector/db/mysql_connector.py
erp_connector/db/oracle_connector.py
erp_connector/db/postgresql_connector.py
erp_connector/exceptions/__init__.py
erp_connector/service/__init__.py
erp_connector/service/connector_service.py
erp_connector/service/event_service.py
erp_connector/utils/InProcessBatch.py
erp_connector/utils/__init__.py
erp_connector/utils/custlogging.py
erp_connector/utils/file_utils.py
erp_connector/utils/mysql_query_utils.py
erp_connector/utils/retryable_session.py
erp_connector/utils/singleton.py