Metadata-Version: 2.1
Name: custom-erp-connector
Version: 0.24
Summary: custom-erp-connector
Home-page: https://github.com/ClearTax/custom-erp-connector
Author: Dinesh Sharma
Author-email: dinesh.sharma@clear.in
